LICENSE
MANIFEST.in
README.md
setup.py
open_llm_benchmark/__init__.py
open_llm_benchmark.egg-info/PKG-INFO
open_llm_benchmark.egg-info/SOURCES.txt
open_llm_benchmark.egg-info/dependency_links.txt
open_llm_benchmark.egg-info/entry_points.txt
open_llm_benchmark.egg-info/requires.txt
open_llm_benchmark.egg-info/top_level.txt
open_llm_benchmark/agent/__init__.py
open_llm_benchmark/agent/react_agent.py
open_llm_benchmark/evaluator/__init__.py
open_llm_benchmark/evaluator/criteria_grader.py
open_llm_benchmark/evaluator/reference_grader.py
open_llm_benchmark/llm/__init__.py
open_llm_benchmark/llm/base.py
open_llm_benchmark/llm/hf_loader.py
open_llm_benchmark/llm/llama_cpp_loader.py
open_llm_benchmark/llm/openai_loader.py
open_llm_benchmark/llm/vllm_loader.py
open_llm_benchmark/task/__init__.py
open_llm_benchmark/task/agent.py
open_llm_benchmark/task/format_output.py
open_llm_benchmark/task/retrieval.py
open_llm_benchmark/task/uber_2021.pdf
test/test_agent.py
test/test_evaluator.py
test/test_llm.py