Metadata-Version: 2.1
Name: open-llm-benchmark
Version: 0.1.0
Summary: Evaluate the capability of open-source LLMs in Agent, formatted output, instruction following, long context retrieval, multilingual, coding, math and custom task.
Home-page: https://github.com/EvilPsyCHo/Open-LLM-Benchmark
Author: ZHIRUI ZHOU
Author-email: evilpsycho42@gmail.com
Requires-Python: >=3.8.4
License-File: LICENSE
